packermate/__init__.py
packermate/aws.py
packermate/command.py
packermate/config.py
packermate/exception.py
packermate/file_utils.py
packermate/process.py
packermate/provisioner.py
packermate/script.py
packermate/target.py
packermate/vagrant.py
packermate/virtualbox.py
packermate/data/packer_virtualbox_iso.json
packermate/data/packer_virtualbox_ovf.json
packermate/data/templates/preseed.cfg.template
packermate-0.16.0.dist-info/DESCRIPTION.rst
packermate-0.16.0.dist-info/METADATA
packermate-0.16.0.dist-info/RECORD
packermate-0.16.0.dist-info/WHEEL
packermate-0.16.0.dist-info/entry_points.txt
packermate-0.16.0.dist-info/metadata.json
packermate-0.16.0.dist-info/pbr.json
packermate-0.16.0.dist-info/top_level.txt
