Metadata-Version: 2.0
Name: packermate
Version: 0.16.0
Summary: Generate and run Packer build configurations from a simple YAML definition
Home-page: https://github.com/wamonite/packermate
Author: Warren Moore
Author-email: warren@wamonite.com
License: MIT
Platform: UNKNOWN
Classifier: Development Status :: 4 - Beta
Classifier: Intended Audience :: Developers
Classifier: Intended Audience :: System Administrators
Classifier: Environment :: Console
Classifier: License :: OSI Approved :: MIT License
Classifier: Natural Language :: English
Classifier: Operating System :: OS Independent
Classifier: Programming Language :: Python :: 2.7
Classifier: Topic :: Utilities
Requires-Dist: pyaml (==16.12.2)
Requires-Dist: requests (==2.18.1)
Requires-Dist: semantic-version (==2.6.0)
Provides-Extra: AWS
Requires-Dist: boto3 (==1.4.4); extra == 'AWS'
